totoro/__init__.py
totoro/amqp.py
totoro/base.py
totoro/redis.py
totoro/test/__init__.py
totoro/test/runtasks.py
totoro/test/runtests.py
totoro/test/celery_tasks/__init__.py
totoro/test/celery_tasks/tasks.py
totoro-0.1.3.dist-info/DESCRIPTION.rst
totoro-0.1.3.dist-info/METADATA
totoro-0.1.3.dist-info/RECORD
totoro-0.1.3.dist-info/WHEEL
totoro-0.1.3.dist-info/metadata.json
totoro-0.1.3.dist-info/top_level.txt
