Metadata-Version: 2.0
Name: totoro
Version: 0.1.3
Summary: Celery integration with Tornado
Home-page: https://github.com/Strawhatfy/totoro
Author: Alex Lee
Author-email: lyd.alexlee.public@gmail.com
License: http://www.apache.org/licenses/LICENSE-2.0
Keywords: tornado,celery,amqp,redis
Platform: UNKNOWN
Classifier: License :: OSI Approved :: Apache Software License
Classifier: Programming Language :: Python :: 2.7
Classifier: Programming Language :: Python :: Implementation :: CPython
Requires-Dist: celery
Requires-Dist: pika
Requires-Dist: tornado
Provides-Extra: redis
Requires-Dist: redis; extra == 'redis'
Requires-Dist: tornado-redis; extra == 'redis'
